<?xml version="1.0" encoding="UTF-8"?>
<DataModel ModuleName="routettpstats" Version="3.4" schemaVersion="3.0"> 
<InstallPath>on_director.datapath.subttp.route.stats</InstallPath>

	<DataModelNode>
                        <InstallPath>routestats</InstallPath>
                        <Name>routestats</Name>
                        <FriendlyName>Route counters</FriendlyName>
                        <NodeID/>
                        <Description>Route counters</Description>
                        <SaveDirName>CM_CONFIG_DIR</SaveDirName>
                        <StorageFileName>NULL</StorageFileName>
                        <NodeAttributes>
                                 <NodeType>CM_DMNODE_TYPE_ANCHOR</NodeType>
                                 <Visible>TRUE</Visible>
                                 <IsKey>FALSE</IsKey>
                                 <Mandatory>FALSE</Mandatory>
                                 <OrderedTable>FALSE</OrderedTable>
                                 <PriorityNode>FALSE</PriorityNode>
                                 <NotifyChange>FALSE</NotifyChange>
                                 <NotifyType>CM_NOT_CHANGEABLE_BY_ACS</NotifyType>
                                 <RebootOnChange>FALSE</RebootOnChange>
                                 <StickyToParent>FALSE</StickyToParent>
                                 <SaveInParentDir>TRUE</SaveInParentDir>
                                 <NonConfigLeafNode>TRUE</NonConfigLeafNode>
                                 <AccessControl>CM_ACCESS_ALL</AccessControl>
                                 <GroupedScalar>TRUE</GroupedScalar>
                                 <GlobalTrans>FALSE</GlobalTrans>
                                 <UseParentTrans>FALSE</UseParentTrans>
                        </NodeAttributes>
                        <DataAttributes>
                                 <DataType>CM_DATA_TYPE_UNKNOWN</DataType>
                                 <Type>CM_DATA_ATTRIB_NONE</Type>
                                 <DataAttrib/>
                        </DataAttributes>
         </DataModelNode>

</DataModel>
